.coveragerc
.mailmap
.testr.conf
AUTHORS
CONTRIBUTING.rst
ChangeLog
HACKING.rst
LICENSE
MANIFEST.in
README.rst
babel.cfg
openstack-common.conf
requirements.txt
setup.cfg
setup.py
test-requirements.txt
tox.ini
devstack/plugin.sh
devstack/settings
devstack/libs/ovs-dpdk
devstack/ovs-dpdk/ovs-dpdk-conf
devstack/ovs-dpdk/ovs-dpdk-init
doc/source/conf.py
doc/source/contributing.rst
doc/source/index.rst
doc/source/installation.rst
doc/source/readme.rst
doc/source/usage.rst
doc/source/usage_puppet.rst
doc/source/_downloads/local.conf.compute_node
doc/source/_downloads/local.conf.controller_node
doc/source/_downloads/local.conf.single_node
doc/source/getstarted/devstack/centos.rst
doc/source/getstarted/devstack/fedora.rst
doc/source/getstarted/devstack/ubuntu.rst
doc/source/getstarted/puppet/ubuntu.rst
etc/policy.json
networking_ovs_dpdk/__init__.py
networking_ovs_dpdk.egg-info/PKG-INFO
networking_ovs_dpdk.egg-info/SOURCES.txt
networking_ovs_dpdk.egg-info/dependency_links.txt
networking_ovs_dpdk.egg-info/entry_points.txt
networking_ovs_dpdk.egg-info/not-zip-safe
networking_ovs_dpdk.egg-info/pbr.json
networking_ovs_dpdk.egg-info/requires.txt
networking_ovs_dpdk.egg-info/top_level.txt
networking_ovs_dpdk/agent/__init__.py
networking_ovs_dpdk/agent/ovs_dpdk_firewall.py
networking_ovs_dpdk/common/__init__.py
networking_ovs_dpdk/common/config.py
networking_ovs_dpdk/common/constants.py
networking_ovs_dpdk/driver/__init__.py
networking_ovs_dpdk/driver/mech_ovs_dpdk.py
networking_ovs_dpdk/tests/__init__.py
networking_ovs_dpdk/tests/unit/__init__.py
networking_ovs_dpdk/tests/unit/agent/test_ovs_dpdk_firewall.py
networking_ovs_dpdk/tests/unit/driver/__init__.py
networking_ovs_dpdk/tests/unit/driver/test_mech_dpdk_ovs.py
puppet/README.md
puppet/ovsdpdk/examples/allinone.pp
puppet/ovsdpdk/examples/compute.pp
puppet/ovsdpdk/examples/controller.pp
puppet/ovsdpdk/examples/openrc
puppet/ovsdpdk/files/build_ovs_dpdk.erb
puppet/ovsdpdk/files/configure_bridges.sh
puppet/ovsdpdk/files/kvm_wrapper
puppet/ovsdpdk/files/numa_filter_append.sh
puppet/ovsdpdk/files/openvswitch-switch.conf
puppet/ovsdpdk/files/openvswitch.service
puppet/ovsdpdk/files/ovs-dpdk-conf.erb
puppet/ovsdpdk/files/patches.erb
puppet/ovsdpdk/files/set_vcpu_pin.sh
puppet/ovsdpdk/files/tune_params.sh
puppet/ovsdpdk/manifests/build_ovs_dpdk.pp
